decimal128/__init__.py
decimal128/decimal128.py
decimal128-1.0.2.dist-info/LICENSE
decimal128-1.0.2.dist-info/METADATA
decimal128-1.0.2.dist-info/WHEEL
decimal128-1.0.2.dist-info/RECORD
