Metadata-Version: 2.1
Name: decimal128
Version: 1.0.2
Summary: 
License: Apache-2.0
Author: Jon Connell
Author-email: python@figsandfudge.com
Requires-Python: >=3.8,<4.0
Classifier: License :: OSI Approved :: Apache Software License
Classifier: Operating System :: OS Independent
Classifier: Programming Language :: Python :: 3
Classifier: Programming Language :: Python :: 3.8
Classifier: Programming Language :: Python :: 3.9
Classifier: Programming Language :: Python :: 3.10
Classifier: Programming Language :: Python :: 3.11
Classifier: Programming Language :: Python :: 3
Project-URL: Documentation, https://github.com/masaccio/decimal128/blob/main/README.md
